mangle-0.0.5.dist-info/METADATA
mangle-0.0.5.dist-info/WHEEL
mangle/__init__.py
mangle/mangle.cpython-39-x86_64-linux-gnu.so
mangle-0.0.5.dist-info/RECORD
