Metadata-Version: 2.1
Name: mangle
Version: 0.0.5
Classifier: Programming Language :: Rust
Classifier: Programming Language :: Python :: Implementation :: CPython
Classifier: Programming Language :: Python :: Implementation :: PyPy
Summary: Python lib for mangle. Exolang that can take any utf8 text as valid code and return some result out of it
Keywords: exolang,python,pyo3,repl
Home-Page: https://mangle.ga
Author: mattf <matheusfillipeag@gmail.com>
Author-email: mattf <matheusfillipeag@gmail.com>
License: MIT
Requires-Python: >=3.7
Project-URL: Source Code, https://github.com/matheusfillipe/mangle
